Metadata-Version: 2.1
Name: talon-v2
Version: 1.0.0
Summary: Mailgun library to extract message quotations and signatures.
Home-page: https://github.com/mailgun/talon
Author: Mailgun Inc.
Author-email: admin@mailgunhq.com
License: APACHE2
Platform: UNKNOWN
License-File: LICENSE
Requires-Dist: lxml (>=2.3.3)
Requires-Dist: regex (>=1)
Requires-Dist: numpy
Requires-Dist: scipy
Requires-Dist: scikit-learn (==0.24.1)
Requires-Dist: chardet (>=1.0.1)
Requires-Dist: cchardet (>=0.3.5)
Requires-Dist: cssselect
Requires-Dist: six (>=1.10.0)
Requires-Dist: html5lib
Requires-Dist: joblib
